ehrml/__init__.py
ehrml/analysis.py
ehrml/binObs.py
ehrml/data2obs.py
ehrml/toNumpy.py
ehrml/transform.py
ehrml/utils.py
ehrml-1.0.3.dist-info/LICENSE
ehrml-1.0.3.dist-info/METADATA
ehrml-1.0.3.dist-info/WHEEL
ehrml-1.0.3.dist-info/top_level.txt
ehrml-1.0.3.dist-info/RECORD
