Metadata-Version: 2.1
Name: ehrml
Version: 1.0.3
Summary: Utilities for using Models with health data.
Author: Ryan Birmingham
Author-email: rbirmin@emory.edu
License: GPL-3
License-File: LICENSE
Requires-Dist: numpy
